dadosfera_logs/__init__.py
dadosfera_logs/dadosfera_logger.py
dadosfera_logs-1.3.0.dist-info/LICENSE
dadosfera_logs-1.3.0.dist-info/METADATA
dadosfera_logs-1.3.0.dist-info/WHEEL
dadosfera_logs-1.3.0.dist-info/RECORD
