Metadata-Version: 2.1
Name: dadosfera_logs
Version: 1.3.0
Summary: Library that you embed into your application to create and manage log events
Author: alexsanderp
Author-email: alexsander.pereira@dadosfera.ai
Requires-Python: >=3.6,<4.0
Classifier: Programming Language :: Python :: 3
Classifier: Programming Language :: Python :: 3.6
Classifier: Programming Language :: Python :: 3.7
Classifier: Programming Language :: Python :: 3.8
Classifier: Programming Language :: Python :: 3.9
Classifier: Programming Language :: Python :: 3.10
Classifier: Programming Language :: Python :: 3.11
Classifier: Programming Language :: Python :: 3.12
Classifier: Programming Language :: Python :: 3.13
Requires-Dist: aws-logging-handlers (>=2.0.5,<3.0.0)
Requires-Dist: boto3 (>=1.23.2,<2.0.0)
Requires-Dist: loguru (>=0.6.0,<0.7.0)
Requires-Dist: pygelf (>=0.4.2,<0.5.0)
